capitains_nautilus/__init__.py
capitains_nautilus/cmd.py
capitains_nautilus/errors.py
capitains_nautilus/flask_ext.py
capitains_nautilus/manager.py
capitains_nautilus/cts/__init__.py
capitains_nautilus/cts/resolver.py
capitains_nautilus/data/templates/cts/Error.xml
capitains_nautilus/data/templates/cts/GetCapabilities.xml
capitains_nautilus/data/templates/cts/GetFirstUrn.xml
capitains_nautilus/data/templates/cts/GetLabel.xml
capitains_nautilus/data/templates/cts/GetPassage.xml
capitains_nautilus/data/templates/cts/GetPassagePlus.xml
capitains_nautilus/data/templates/cts/GetPrevNext.xml
capitains_nautilus/data/templates/cts/GetValidReff.xml
capitains_nautilus-1.0.2.dist-info/DESCRIPTION.rst
capitains_nautilus-1.0.2.dist-info/METADATA
capitains_nautilus-1.0.2.dist-info/RECORD
capitains_nautilus-1.0.2.dist-info/WHEEL
capitains_nautilus-1.0.2.dist-info/entry_points.txt
capitains_nautilus-1.0.2.dist-info/metadata.json
capitains_nautilus-1.0.2.dist-info/top_level.txt
