Metadata-Version: 2.0
Name: capitains-nautilus
Version: 1.0.2
Summary: Resolver for Capitains Guidelines Repository
Home-page: http://github.com/Capitains/nautilus
Author: Thibault Clerice
Author-email: leponteineptique@gmail.com
License: Mozilla Public License Version 2.0
Platform: UNKNOWN
Requires-Dist: MyCapytain (>=2.0.0)
Requires-Dist: tornado (>=4.3)
Requires-Dist: Flask (>=0.12)
Requires-Dist: Werkzeug (>=0.11.3)
Requires-Dist: redis (>=2.10.5)
Requires-Dist: Flask-Caching (==1.2.0)
